CHANGES.txt
LICENSE.txt
MANIFEST.in
README.txt
ez_setup.py
setup.py
rod/__init__.py
rod.recipe.py2app.egg-info/PKG-INFO
rod.recipe.py2app.egg-info/SOURCES.txt
rod.recipe.py2app.egg-info/dependency_links.txt
rod.recipe.py2app.egg-info/entry_points.txt
rod.recipe.py2app.egg-info/namespace_packages.txt
rod.recipe.py2app.egg-info/requires.txt
rod.recipe.py2app.egg-info/top_level.txt
rod.recipe.py2app.egg-info/zip-safe
rod/recipe/__init__.py
rod/recipe/py2app/README.txt
rod/recipe/py2app/__init__.py
rod/recipe/py2app/tests.py