Metadata-Version: 1.0
Name: rod.recipe.py2app
Version: 1.0.0
Summary: ZC Buildout recipe for building standalone Mac OS X application bundles.
Home-page: http://cheeseshop.python.org/pypi/rod.recipe.py2app
Author: Tobias Rodaebel
Author-email: tobias.rodaebel at googlemail dot net
License: GPLv3
Keywords: pyobjc zc.buildout recipe
Platform: UNKNOWN
Classifier: Framework :: Buildout
Classifier: Intended Audience :: Developers
Classifier: License :: OSI Approved :: GNU General Public License (GPL)
Classifier: Topic :: Software Development :: Build Tools
Classifier: Topic :: Software Development :: Libraries :: Python Modules
